odoo/addons/purchase_order_line_original_date/README.rst
odoo/addons/purchase_order_line_original_date/__init__.py
odoo/addons/purchase_order_line_original_date/__manifest__.py
odoo/addons/purchase_order_line_original_date/i18n/it.po
odoo/addons/purchase_order_line_original_date/i18n/purchase_order_line_original_date.pot
odoo/addons/purchase_order_line_original_date/models/__init__.py
odoo/addons/purchase_order_line_original_date/models/purchase_order.py
odoo/addons/purchase_order_line_original_date/models/purchase_order_line.py
odoo/addons/purchase_order_line_original_date/readme/CONTRIBUTORS.md
odoo/addons/purchase_order_line_original_date/readme/DESCRIPTION.md
odoo/addons/purchase_order_line_original_date/readme/USAGE.md
odoo/addons/purchase_order_line_original_date/static/description/icon.png
odoo/addons/purchase_order_line_original_date/static/description/index.html
odoo/addons/purchase_order_line_original_date/tests/__init__.py
odoo/addons/purchase_order_line_original_date/tests/test_purchase_order_line_original_date.py
odoo/addons/purchase_order_line_original_date/views/purchase_order_line_views.xml
odoo/addons/purchase_order_line_original_date/views/purchase_order_views.xml
odoo_addon_purchase_order_line_original_date-18.0.1.0.0.4.dist-info/METADATA
odoo_addon_purchase_order_line_original_date-18.0.1.0.0.4.dist-info/WHEEL
odoo_addon_purchase_order_line_original_date-18.0.1.0.0.4.dist-info/top_level.txt
odoo_addon_purchase_order_line_original_date-18.0.1.0.0.4.dist-info/RECORD
